tu_games/__init__.py
tu_games/game.py
tu_games-1.0.2.dist-info/METADATA
tu_games-1.0.2.dist-info/WHEEL
tu_games-1.0.2.dist-info/licenses/LICENSE
tu_games-1.0.2.dist-info/RECORD
